[
  {
    "page_id": 101,
    "type": "text",
    "output_txt": "위이잉- 위이잉-",
    "relate_value": null,
    "occur_condition": null,
    "occur_value": [],
    "occur_prob": null,
    "result_value": [],
    "result_count": null,
    "result_prob": [],
    "is_renew_page": null
  },
  {
    "page_id": 101,
    "type": "text",
    "output_txt": "평화로운 휴일, 머리맡에 놓아둔 휴대폰이 시끄럽게 울립니다. 늦잠을 자던 당신은 비몽사몽 하며 눈을 비비다, 휴대폰을 확인했습니다.",
    "relate_value": null,
    "occur_condition": null,
    "occur_value": [],
    "occur_prob": null,
    "result_value": [],
    "result_count": null,
    "result_prob": [],
    "is_renew_page": null
  },
  {
    "page_id": 101,
    "type": "img",
    "output_txt": null,
    "relate_value": "img_phone",
    "occur_condition": null,
    "occur_value": [],
    "occur_prob": null,
    "result_value": [],
    "result_count": null,
    "result_prob": [],
    "is_renew_page": null
  },
  {
    "page_id": 101,
    "type": "text",
    "output_txt": " - [긴급재난문자] 정체불명의 괴물체 및 괴현상 출현. 시민 여러분께서는 안전을 위해 가까운 대피소로 대피 바랍니다.",
    "relate_value": null,
    "occur_condition": null,
    "occur_value": [],
    "occur_prob": null,
    "result_value": [],
    "result_count": null,
    "result_prob": [],
    "is_renew_page": null
  },
  {
    "page_id": 101,
    "type": "button",
    "output_txt": "뭐야, 이건…? 오발송인가?",
    "relate_value": null,
    "occur_condition": null,
    "occur_value": [],
    "occur_prob": null,
    "result_value": [1011, 1012, 1013],
    "result_count": null,
    "result_prob": [1,1,1],
    "is_renew_page": null
  },
  {
    "page_id": 101,
    "type": "button",
    "output_txt": "대피하라고? 뭔진 모르겠지만 일단 나가자…!",
    "relate_value": null,
    "occur_condition": null,
    "occur_value": [],
    "occur_prob": null,
    "result_value": [1014],
    "result_count": null,
    "result_prob": [],
    "is_renew_page": null
  },
  {
    "page_id": 101,
    "type": "battle",
    "output_txt": "전투 테스트용 테스트 버튼",
    "relate_value": null,
    "occur_condition": null,
    "occur_value": [],
    "occur_prob": null,
    "result_value": [10001, 1011],
    "result_count": null,
    "result_prob": [],
    "is_renew_page": null
  },
  {
    "page_id": 1011,
    "type": "text",
    "output_txt": "당신은 재난 문자를 대수롭지 않게 여겼습니다. 보나마나 별것 아닐 게 분명했으니까요. 하지만 재난 문자를 확인하느라 잠이 확 깨 버렸네요.\n당신은 침대에서 일어나 기지개를 켜고 SNS에 들어갔습니다. 그런데… 최근 게시물에 낯선 영상이 보이는군요?\n[미친; 살려줘 ㅅㅂ..\n댓글: 뭐야 실제임?????\n댓글: 야 이거 찍은애 죽은 거 아니냐..\n댓글: CG 아니고 진짜라고??\n댓글: 이야 요즘 영화 홍보 신박하게 하넼ㅋㅋㅋㅋ\n댓글: 이거 영화 아니고 실제임;;]\n게임에서나 나올 법한 괴생명체가 찍힌 영상. 방금 받은 재난 문자를 떠올리며, 당신은 SNS를 빠르게 훑었습니다. 그런데 아무래도… 영상 속 상황이 실제인 것 같습니다.",
    "relate_value": null,
    "occur_condition": null,
    "occur_value": [],
    "occur_prob": null,
    "result_value": [],
    "result_count": null,
    "result_prob": [],
    "is_renew_page": null
  },
  {
    "page_id": 1011,
    "type": "button",
    "output_txt": "다음",
    "relate_value": null,
    "occur_condition": null,
    "occur_value": [],
    "occur_prob": null,
    "result_value": [102],
    "result_count": null,
    "result_prob": [],
    "is_renew_page": null
  },
  {
    "page_id": 1012,
    "type": "text",
    "output_txt": "당신은 재난 문자를 대수롭지 않게 여겼습니다. 언제나 그렇듯이 별것 아닐 거라고 생각했어요. 그런데 재난 문자를 확인하느라 잠이 확 깨 버렸군요.\n당신은 잠시 침대에 앉아 있다가 거실로 나가 TV를 켰습니다.\n[<속보> 전세계 곳곳에서 괴현상 발생]\n그런데 예능 화면 위에 떠 있는 뉴스 속보 자막. 방금 받은 재난 문자가 떠오르며 왠지 모를 불길함이 느껴집니다. 자각할 새도 없이, 당신의 손이 채널을 돌려 뉴스를 틀었습니다.\n\"…뿐만 아니라 괴생명체가 출현하여 시민들을 공격하고 있으며, 정부가 빠르게 군대를 동원하여…\"\n괴생명체, 정부, 군대…. TV에서는 믿기지 않는 이야기들이 쏟아지고 있었습니다. 대체 이게 무슨 일일까요…?\n너무나도 혼란스럽지만 한 가지는 분명했습니다. 바로 이 믿기지 않는 이야기들을 사실이라고 받아들여야 한다는 것 말이에요.",
    "relate_value": null,
    "occur_condition": null,
    "occur_value": [],
    "occur_prob": null,
    "result_value": [],
    "result_count": null,
    "result_prob": [],
    "is_renew_page": null
  },
  {
    "page_id": 1012,
    "type": "button",
    "output_txt": "다음",
    "relate_value": null,
    "occur_condition": null,
    "occur_value": [],
    "occur_prob": null,
    "result_value": [102],
    "result_count": null,
    "result_prob": [],
    "is_renew_page": null
  },
  {
    "page_id": 1013,
    "type": "text",
    "output_txt": "당신은 재난 문자를 대수롭지 않게 여겼습니다. 재난 문자가 오는 건 종종 있는 일이었으니까요. 내용이 평소와 좀 다르긴 하지만… 별일은 아닐 것 같습니다. 그보다는 재난 문자 때문에 잠이 확 달아나 버린 게 큰일이죠.\n늦잠을 방해 받은 당신은 한숨을 푹 쉬고 침대에서 일어나 기지개를 켰습니다.\n쿠구궁-\n그런데 갑자기 밭 밑에서 진동이 느껴지네요. 낯선 감각에 순간 심장이 철렁한 당신은 반사적으로 창문 너머 바깥을 쳐다봤습니다.",
    "relate_value": null,
    "occur_condition": null,
    "occur_value": [],
    "occur_prob": null,
    "result_value": [],
    "result_count": null,
    "result_prob": [],
    "is_renew_page": null
  },
  {
    "page_id": 1013,
    "type": "img",
    "output_txt": null,
    "relate_value": "img_purple_sky",
    "occur_condition": null,
    "occur_value": [],
    "occur_prob": null,
    "result_value": [],
    "result_count": null,
    "result_prob": [],
    "is_renew_page": null
  },
  {
    "page_id": 1013,
    "type": "text",
    "output_txt": "당신의 시야에 가득 들어오는 보랏빛 하늘. 당신은 그제야 하늘이 기묘한 빛을 띠고 있다는 걸 깨달았습니다.\n설마… 방금 받은 재난 문자와 관련 있는 걸까요? 어쩌면 그 재난 문자는 잘못 보낸 게 아닐지도 모른다고, 당신은 뒤늦게 생각했습니다.",
    "relate_value": null,
    "occur_condition": null,
    "occur_value": [],
    "occur_prob": null,
    "result_value": [],
    "result_count": null,
    "result_prob": [],
    "is_renew_page": null
  },
  {
    "page_id": 1013,
    "type": "button",
    "output_txt": "다음",
    "relate_value": null,
    "occur_condition": null,
    "occur_value": [],
    "occur_prob": null,
    "result_value": [102],
    "result_count": null,
    "result_prob": [],
    "is_renew_page": null
  },
  {
    "page_id": 1014,
    "type": "text",
    "output_txt": "괴물체라는 게 뭔지 잘은 모르겠지만, 아무래도 재난 문자의 내용이 심상치 않아 보입니다. 당신은 바로 자리를 박차고 일어났어요. 재난 문자가, 그것도 대피하라는 내용의 문자가 온 것을 보고도 무시할 수는 없었으니까요.",
    "relate_value": null,
    "occur_condition": null,
    "occur_value": [],
    "occur_prob": null,
    "result_value": [],
    "result_count": null,
    "result_prob": [],
    "is_renew_page": null
  },
  {
    "page_id": 1014,
    "type": "button",
    "output_txt": "다음",
    "relate_value": null,
    "occur_condition": null,
    "occur_value": [],
    "occur_prob": null,
    "result_value": [102],
    "result_count": null,
    "result_prob": [],
    "is_renew_page": null
  },
  {
    "page_id": 102,
    "type": "text",
    "output_txt": "빠르게 외출복으로 갈아입은 당신은 핸드폰을 손에 쥐고 현관으로 달려 나갔습니다. 그런데 문득 멈추는 당신의 걸음.",
    "relate_value": null,
    "occur_condition": null,
    "occur_value": [],
    "occur_prob": null,
    "result_value": [],
    "result_count": null,
    "result_prob": [],
    "is_renew_page": true
  },
  {
    "page_id": 102,
    "type": "button",
    "output_txt": "이대로 나가면 안 될 것 같은데…",
    "relate_value": null,
    "occur_condition": null,
    "occur_value": [],
    "occur_prob": null,
    "result_value": [103],
    "result_count": null,
    "result_prob": [],
    "is_renew_page": null
  },
  {
    "page_id": 103,
    "type": "recursive_group",
    "output_txt": "당신은 현관 앞에 서서 주변을 살며시 둘러봤습니다. 뭔가 챙길 것이 없을까, 고민하는 당신의 시선이 빠르게 집 안을 훑습니다.",
    "relate_value": null,
    "occur_condition": null,
    "occur_value": [],
    "occur_prob": null,
    "result_value": [1031, 1032, 1033, 1034, 1035],
    "result_count": 3,
    "result_prob": [1,1,1,1,1],
    "is_renew_page": true
  },
  {
    "page_id": 1031,
    "type": "button",
    "output_txt": "우산",
    "relate_value": null,
    "occur_condition": null,
    "occur_value": [],
    "occur_prob": null,
    "result_value": [10311],
    "result_count": null,
    "result_prob": [],
    "is_renew_page": null
  },
  {
    "page_id": 1032,
    "type": "button",
    "output_txt": "구급약품",
    "relate_value": null,
    "occur_condition": null,
    "occur_value": [],
    "occur_prob": null,
    "result_value": [10321],
    "result_count": null,
    "result_prob": [],
    "is_renew_page": null
  },
  {
    "page_id": 1033,
    "type": "button",
    "output_txt": "기타",
    "relate_value": null,
    "occur_condition": null,
    "occur_value": [],
    "occur_prob": null,
    "result_value": [10331],
    "result_count": null,
    "result_prob": [],
    "is_renew_page": null
  },
  {
    "page_id": 1034,
    "type": "button",
    "output_txt": "망치",
    "relate_value": null,
    "occur_condition": null,
    "occur_value": [],
    "occur_prob": null,
    "result_value": [10341],
    "result_count": null,
    "result_prob": [],
    "is_renew_page": null
  },
  {
    "page_id": 1035,
    "type": "button",
    "output_txt": "골프채",
    "relate_value": null,
    "occur_condition": null,
    "occur_value": [],
    "occur_prob": null,
    "result_value": [10351],
    "result_count": null,
    "result_prob": [],
    "is_renew_page": null
  },
  {
    "page_id": 10311,
    "type": "text",
    "output_txt": "당신은 현관 앞 바구니에 꽂혀 있던 우산을 꺼내 들었습니다.",
    "relate_value": null,
    "occur_condition": null,
    "occur_value": [],
    "occur_prob": null,
    "result_value": [],
    "result_count": null,
    "result_prob": [],
    "is_renew_page": null
  },
  {
    "page_id": 10311,
    "type": "button",
    "output_txt": "여차하면 무기로도 쓸 수 있을 거야.",
    "relate_value": null,
    "occur_condition": null,
    "occur_value": [],
    "occur_prob": null,
    "result_value": [104],
    "result_count": null,
    "result_prob": [],
    "is_renew_page": null
  },
  {
    "page_id": 10321,
    "type": "text",
    "output_txt": "당신은 거실장에 놓여 있던 구급약품을 챙겼습니다.",
    "relate_value": null,
    "occur_condition": null,
    "occur_value": [],
    "occur_prob": null,
    "result_value": [],
    "result_count": null,
    "result_prob": [],
    "is_renew_page": null
  },
  {
    "page_id": 10321,
    "type": "button",
    "output_txt": "혹시 다칠지도 모르니까…!",
    "relate_value": null,
    "occur_condition": null,
    "occur_value": [],
    "occur_prob": null,
    "result_value": [104],
    "result_count": null,
    "result_prob": [],
    "is_renew_page": null
  },
  {
    "page_id": 10331,
    "type": "text",
    "output_txt": "당신은 취미로 샀다가 방치해 둔 기타를 꺼냈습니다.",
    "relate_value": null,
    "occur_condition": null,
    "occur_value": [],
    "occur_prob": null,
    "result_value": [],
    "result_count": null,
    "result_prob": [],
    "is_renew_page": null
  },
  {
    "page_id": 10331,
    "type": "button",
    "output_txt": "나름 튼튼하니까 무기로 쓸 수 있을지도 몰라.",
    "relate_value": null,
    "occur_condition": null,
    "occur_value": [],
    "occur_prob": null,
    "result_value": [104],
    "result_count": null,
    "result_prob": [],
    "is_renew_page": null
  },
  {
    "page_id": 10341,
    "type": "text",
    "output_txt": "당신은 현관 앞 수납장에 들어 있던 망치를 꺼내 들었습니다.",
    "relate_value": null,
    "occur_condition": null,
    "occur_value": [],
    "occur_prob": null,
    "result_value": [],
    "result_count": null,
    "result_prob": [],
    "is_renew_page": null
  },
  {
    "page_id": 10341,
    "type": "button",
    "output_txt": "뭔가 부술 일이 생길 수도 있으니까…!",
    "relate_value": null,
    "occur_condition": null,
    "occur_value": [],
    "occur_prob": null,
    "result_value": [104],
    "result_count": null,
    "result_prob": [],
    "is_renew_page": null
  },
  {
    "page_id": 10351,
    "type": "text",
    "output_txt": "당신은 안방에서 아버지의 골프채를 꺼내 왔습니다.",
    "relate_value": null,
    "occur_condition": null,
    "occur_value": [],
    "occur_prob": null,
    "result_value": [],
    "result_count": null,
    "result_prob": [],
    "is_renew_page": null
  },
  {
    "page_id": 10351,
    "type": "button",
    "output_txt": "무기로 쓰기엔 이게 최고지.",
    "relate_value": null,
    "occur_condition": null,
    "occur_value": [],
    "occur_prob": null,
    "result_value": [104],
    "result_count": null,
    "result_prob": [],
    "is_renew_page": null
  },
  {
    "page_id": 104,
    "type": "text",
    "output_txt": "위이잉- 위이잉-",
    "relate_value": null,
    "occur_condition": null,
    "occur_value": [],
    "occur_prob": null,
    "result_value": [],
    "result_count": null,
    "result_prob": [],
    "is_renew_page": true
  },
  {
    "page_id": 104,
    "type": "text",
    "output_txt": " - [긴급재난문자] 괴물체 및 괴현상 출현 중. 시민 여러분께서는 가까운 대피소로 대피 바랍니다.",
    "relate_value": null,
    "occur_condition": null,
    "occur_value": [],
    "occur_prob": null,
    "result_value": [],
    "result_count": null,
    "result_prob": [],
    "is_renew_page": null
  },
  {
    "page_id": 104,
    "type": "text",
    "output_txt": "현관 앞에서 머뭇거리는 당신을 채찍질하듯, 다시 한번 재난 문자가 울립니다. 더는 시간을 지체할 수 없을 것 같아요.\n당신은 저도 모르게 심호흡을 내뱉었습니다. 그리고 마침내, 신발을 신고 현관문을 열었습니다.",
    "relate_value": null,
    "occur_condition": null,
    "occur_value": [],
    "occur_prob": null,
    "result_value": [],
    "result_count": null,
    "result_prob": [],
    "is_renew_page": null
  },
  {
    "page_id": 104,
    "type": "button",
    "output_txt": "뭐가 뭔지 모르겠지만 일단 나가자…!",
    "relate_value": null,
    "occur_condition": null,
    "occur_value": [],
    "occur_prob": null,
    "result_value": [105],
    "result_count": null,
    "result_prob": [],
    "is_renew_page": null
  },
  {
    "page_id": 105,
    "type": "text",
    "output_txt": "밖으로 나오자, 당신과 마찬가지로 재난 문자를 받고 뛰쳐나온 사람들이 가득 보입니다. 다들 이 상황이 당황스러운지 우왕좌왕하고 있네요.\n \"대, 대피소가 어디예요…?\"\n \"괴물체라니 이게 대체 무슨 소리요?!\"\n \"여기에서 제일 가까운 대피소가…\"\n \"흑, 엄마…\"\n사람들은 저마다 자기 할 말만 늘어놓았습니다. 그중에는 가족을 찾는 사람들도 적지 않았어요. 그러고 보니 당신의 부모님도 오전부터 외출을 나갔습니다. 당신의 부모님은 이 상황을 알고 있는 걸까요?",
    "relate_value": null,
    "occur_condition": null,
    "occur_value": [],
    "occur_prob": null,
    "result_value": [],
    "result_count": null,
    "result_prob": [],
    "is_renew_page": true
  },
  {
    "page_id": 105,
    "type": "button",
    "output_txt": "맞아, 그러고 보니까 엄마, 아빠는…?",
    "relate_value": null,
    "occur_condition": null,
    "occur_value": [],
    "occur_prob": null,
    "result_value": [106],
    "result_count": null,
    "result_prob": [],
    "is_renew_page": null
  },
  {
    "page_id": 106,
    "type": "text",
    "output_txt": "당신은 사람들을 따라 대피소로 이동하면서 어머니에게 전화를 걸었습니다.\n - 여보세요? 너 지금 어디니...! 괜찮은 거지…?\n짧은 연결음 끝에 들려오는 어머니의 목소리. 순간 당신의 입에서 안도의 한숨이 새어 나옵니다.",
    "relate_value": null,
    "occur_condition": null,
    "occur_value": [],
    "occur_prob": null,
    "result_value": [],
    "result_count": null,
    "result_prob": [],
    "is_renew_page": true
  },
  {
    "page_id": 106,
    "type": "button",
    "output_txt": "응, 엄마… 난 괜찮아.",
    "relate_value": null,
    "occur_condition": null,
    "occur_value": [],
    "occur_prob": null,
    "result_value": [107],
    "result_count": null,
    "result_prob": [],
    "is_renew_page": null
  },
  {
    "page_id": 107,
    "type": "text",
    "output_txt": " - 다행이다… 엄마, 아빠도 괜찮아…! 대피소로 피하고 있-\n - 쿠르릉-!\n - 여보…!\n전화 너머에서 굉음이 들려오더니 전화가 뚝- 끊어졌습니다. 이게 대체 어떻게 된 일일까요? 부모님은… 무사한 거겠죠?",
    "relate_value": null,
    "occur_condition": null,
    "occur_value": [],
    "occur_prob": null,
    "result_value": [],
    "result_count": null,
    "result_prob": [],
    "is_renew_page": true
  },
  {
    "page_id": 107,
    "type": "button",
    "output_txt": "엄마…?",
    "relate_value": null,
    "occur_condition": null,
    "occur_value": [],
    "occur_prob": null,
    "result_value": [108],
    "result_count": null,
    "result_prob": [],
    "is_renew_page": null
  },
  {
    "page_id": 108,
    "type": "text",
    "output_txt": "다시 전화를 걸어 봤지만 당신의 어머니는 전화를 받지 않았습니다.\n쿠궁-! 콰과광-!!\n \"꺄악…!\"\n \"으아악…! 저, 저게 뭐야…?!!\"\n \"도, 도망쳐…!!\"\n다시 한번 부모님에게 전화를 걸려는데, 사람들이 비명을 지르며 달아나기 시작합니다. 전화에 정신이 팔려 상황을 이해하지 못한 당신은 멍하니 앞을 바라보았습니다.\n얼마 전까지 당신이 있던 곳, 멀지 않은 거리에 있는 아파트 단지 쪽에서 불길하게 소용돌이 치는 빛무리가 보입니다. 그리고... 그 너머에서 나오는 괴물들까지도요.",
    "relate_value": null,
    "occur_condition": null,
    "occur_value": [],
    "occur_prob": null,
    "result_value": [],
    "result_count": null,
    "result_prob": [],
    "is_renew_page": null
  },
  {
    "page_id": 108,
    "type": "button",
    "output_txt": "...도망쳐야 돼.",
    "relate_value": null,
    "occur_condition": null,
    "occur_value": [],
    "occur_prob": null,
    "result_value": [109],
    "result_count": null,
    "result_prob": [],
    "is_renew_page": null
  },
  {
    "page_id": 109,
    "type": "text",
    "output_txt": "당신은 본능적으로 몸을 움직였습니다. 다행히 빛무리가 점점 멀어지면서 작게 보이네요.",
    "relate_value": null,
    "occur_condition": null,
    "occur_value": [],
    "occur_prob": null,
    "result_value": [],
    "result_count": null,
    "result_prob": [],
    "is_renew_page": true
  },
  {
    "page_id": 109,
    "type": "button",
    "output_txt": "다른 사람들이랑 같이 움직이자.",
    "relate_value": null,
    "occur_condition": null,
    "occur_value": [],
    "occur_prob": null,
    "result_value": [1091],
    "result_count": null,
    "result_prob": [],
    "is_renew_page": null
  },
  {
    "page_id": 109,
    "type": "button",
    "output_txt": "혼자 움직이는 게 나을 것 같아.",
    "relate_value": null,
    "occur_condition": null,
    "occur_value": [],
    "occur_prob": null,
    "result_value": [1096],
    "result_count": null,
    "result_prob": [],
    "is_renew_page": null
  },
  {
    "page_id": 1091,
    "type": "text",
    "output_txt": "당신은 정신 없이 도망치는 사람들과 함께 길을 달렸습니다.\n콰광-\n \"대, 대피소로…! 얼른…!!\"\n \"조금만 가면 대피소야…!\"\n쿵- 쿠궁-\n대피소는 정말로 안전한 게 맞을까요? 밀려오는 불안을 애써 무시하며, 당신은 대피소를 향해 갔습니다.",
    "relate_value": null,
    "occur_condition": null,
    "occur_value": [],
    "occur_prob": null,
    "result_value": [],
    "result_count": null,
    "result_prob": [],
    "is_renew_page": true
  },
  {
    "page_id": 1091,
    "type": "button",
    "output_txt": "다음",
    "relate_value": null,
    "occur_condition": null,
    "occur_value": [],
    "occur_prob": null,
    "result_value": [1092],
    "result_count": null,
    "result_prob": [],
    "is_renew_page": null
  },
  {
    "page_id": 1092,
    "type": "text",
    "output_txt": "대피소가 멀지 않은 곳에 있어서, 당신을 포함한 많은 사람들이 곧 대피소에 도착했습니다. 그런데 대피소는 이미 사람들로 가득해 보입니다.\n들어가려면 들어갈 수는 있지만… 저 많은 사람들 틈에 있고 싶지 않군요. 게다가 대피소라고 해도 그저 커다란 강당일 뿐… 괴물에 대응할 만한 게 있어 보이지도 않습니다.",
    "relate_value": null,
    "occur_condition": null,
    "occur_value": [],
    "occur_prob": null,
    "result_value": [],
    "result_count": null,
    "result_prob": [],
    "is_renew_page": null
  },
  {
    "page_id": 1092,
    "type": "button",
    "output_txt": "…여기 있어 봤자 아무것도 못 할 것 같아.",
    "relate_value": null,
    "occur_condition": null,
    "occur_value": [],
    "occur_prob": null,
    "result_value": [1093],
    "result_count": null,
    "result_prob": [],
    "is_renew_page": null
  },
  {
    "page_id": 1093,
    "type": "text",
    "output_txt": "당신은 아까부터 계속 손에 들고 있던 휴대폰을 세게 움켜쥐었습니다. 문득, 갑자기 끊어졌던 어머니의 전화가 떠오르네요.",
    "relate_value": null,
    "occur_condition": null,
    "occur_value": [],
    "occur_prob": null,
    "result_value": [],
    "result_count": null,
    "result_prob": [],
    "is_renew_page": true
  },
  {
    "page_id": 1093,
    "type": "button",
    "output_txt": "차라리 엄마, 아빠를 보러 가는 게 낫지 않을까?",
    "relate_value": null,
    "occur_condition": null,
    "occur_value": [],
    "occur_prob": null,
    "result_value": [1094],
    "result_count": null,
    "result_prob": [],
    "is_renew_page": null
  },
  {
    "page_id": 1094,
    "type": "text",
    "output_txt": "괴물을 상대할 자신은 없지만, 이곳에서 무의미하게 시간을 보내는 것보다는 부모님을 만나러 가는 게 낫지 않을까요? 불길한 생각을 하고 싶지는 않지만... 어쩌면 영영 부모님을 못 보게 될지도 모르고요.\n당신은 부모님을 볼 수 있는 가능성이 조금이라도 있는 쪽을 택하고 싶었습니다. 설사 그게 위험에 빠지는 길이라 할지라도요.",
    "relate_value": null,
    "occur_condition": null,
    "occur_value": [],
    "occur_prob": null,
    "result_value": [],
    "result_count": null,
    "result_prob": [],
    "is_renew_page": null
  },
  {
    "page_id": 1094,
    "type": "button",
    "output_txt": "나가자. 가서 엄마, 아빠를 찾는 거야.",
    "relate_value": null,
    "occur_condition": null,
    "occur_value": [],
    "occur_prob": null,
    "result_value": [1095],
    "result_count": null,
    "result_prob": [],
    "is_renew_page": null
  },
  {
    "page_id": 1095,
    "type": "text",
    "output_txt": "당신은 미련 없이 몸을 돌렸습니다. 혹시 괴물들이 튀어 나올 수도 있으니까 조심조심 움직였어요.\n콰앙-\n그런데 어느 순간, 뒤에서 시끄러운 소리가 들려옵니다. 뒤를 돌아보자 대피소로 몰려든 사람들과… 그들을 쫓아온 괴물들이 보이는군요.\n쿵-\n괴물의 공격을 받은 대피소 건물 벽이 부서집니다. 사람들의 비명이 당신이 있는 곳까지 들려왔습니다. 짙은 공포가 느껴지는 비명 소리들. 저 대피소에서 무슨 일이 벌어졌을지… 차마 생각할 엄두도 나지 않네요.\n최대한 많은 사람들이 무사하기를 빌며, 당신은 빠르게 대피소에서 멀어졌습니다.",
    "relate_value": null,
    "occur_condition": null,
    "occur_value": [],
    "occur_prob": null,
    "result_value": [],
    "result_count": null,
    "result_prob": [],
    "is_renew_page": true
  },
  {
    "page_id": 1095,
    "type": "button",
    "output_txt": "다음",
    "relate_value": null,
    "occur_condition": null,
    "occur_value": [],
    "occur_prob": null,
    "result_value": [],
    "result_count": null,
    "result_prob": [],
    "is_renew_page": null
  },
  {
    "page_id": 1096,
    "type": "text",
    "output_txt": "당신은 사람이 적은 샛길로 빠졌습니다. 서로 밀치며 도망치기 바쁜 사람들 틈에 섞여 있는 건 아무리 생각해도 도움이 될 것 같지 않았어요. 어차피 대피소로 가는 길은 하나가 아니니까, 차분하게 주변을 살피면서 가는 것도 나쁘지 않을 거예요.",
    "relate_value": null,
    "occur_condition": null,
    "occur_value": [],
    "occur_prob": null,
    "result_value": [],
    "result_count": null,
    "result_prob": [],
    "is_renew_page": true
  },
  {
    "page_id": 1096,
    "type": "button",
    "output_txt": "다음",
    "relate_value": null,
    "occur_condition": null,
    "occur_value": [],
    "occur_prob": null,
    "result_value": [1097],
    "result_count": null,
    "result_prob": [],
    "is_renew_page": null
  },
  {
    "page_id": 1097,
    "type": "text",
    "output_txt": "잠시 후, 당신은 대피소 근처에 도착했습니다. 하지만 당신은 더 이상 앞으로 나아가지 못하고 멈춰 있었어요. 왜냐하면…\n콰광-\n \"꺄악…!\"\n \"안으로 들어가게 해 줘, 제발…!!\"\n \"누, 누가 좀… 으아아악!\"\n당신보다 먼저 대피소에 도착한 사람들을 쫓아온 듯 보이는 괴물들이, 대피소를 공격하고 있었기 때문이죠.",
    "relate_value": null,
    "occur_condition": null,
    "occur_value": [],
    "occur_prob": null,
    "result_value": [],
    "result_count": null,
    "result_prob": [],
    "is_renew_page": null
  },
  {
    "page_id": 1097,
    "type": "button",
    "output_txt": "...대피소도 안전하지 않아.",
    "relate_value": null,
    "occur_condition": null,
    "occur_value": [],
    "occur_prob": null,
    "result_value": [1098],
    "result_count": null,
    "result_prob": [],
    "is_renew_page": null
  },
  {
    "page_id": 1098,
    "type": "text",
    "output_txt": "당신은 대피소라고 해서 안전한 곳이 아님을 깨닫고, 괴물들을 피해 벽 뒤로 몸을 숨겼다. 공포 때문일까요? 휴대폰을 쥔 손에 힘이 들어갑니다. 문득, 아까 전 갑작스럽게 끊어졌던 어머니의 전화가 떠오르네요.",
    "relate_value": null,
    "occur_condition": null,
    "occur_value": [],
    "occur_prob": null,
    "result_value": [],
    "result_count": null,
    "result_prob": [],
    "is_renew_page": null
  },
  {
    "page_id": 1098,
    "type": "button",
    "output_txt": "…차라리 엄마, 아빠를 찾자.",
    "relate_value": null,
    "occur_condition": null,
    "occur_value": [],
    "occur_prob": null,
    "result_value": [],
    "result_count": null,
    "result_prob": [],
    "is_renew_page": null
  },
  {
    "page_id": 1099,
    "type": "text",
    "output_txt": "대피소도 위험한 건 마찬가지라면, 부모님을 만나러 가는 게 낫지 않을까요? 불길한 생각을 하고 싶지는 않지만... 어쩌면 영영 부모님을 못 보게 될지도 모르고요.\n결심을 마친 당신은 미련 없이 돌아섰습니다. 대피소가 있는 뒤쪽에서 들려오던 사람들의 비명 소리가 조금씩 옅어집니다.",
    "relate_value": null,
    "occur_condition": null,
    "occur_value": [],
    "occur_prob": null,
    "result_value": [],
    "result_count": null,
    "result_prob": [],
    "is_renew_page": true
  },
  {
    "page_id": 1099,
    "type": "button",
    "output_txt": "다음",
    "relate_value": null,
    "occur_condition": null,
    "occur_value": [],
    "occur_prob": null,
    "result_value": [],
    "result_count": null,
    "result_prob": [],
    "is_renew_page": null
  }
]