[
  {
    "page_id": 101,
    "type": "text",
    "output_txt": "여느 때와 같은 휴일, 당신은 휴대폰 진동 소리에 잠에서 깨어났다.",
    "relate_value": null,
    "occur_condition": null,
    "occur_value": [],
    "occur_prob": null,
    "result_value": [],
    "result_count": null,
    "result_prob": [],
    "is_renew_page": true
  },
  {
    "page_id": 101,
    "type": "img",
    "output_txt": null,
    "relate_value": "img_phone",
    "occur_condition": null,
    "occur_value": [],
    "occur_prob": null,
    "result_value": [],
    "result_count": null,
    "result_prob": [],
    "is_renew_page": null
  },
  {
    "page_id": 101,
    "type": "text",
    "output_txt": "지이잉-\n\"절대 집에서 나오지 마! 알았지? 엄마 말 들어…!\"\n뭐라 대답할 틈도 없이 다급하게 흘러나온 스피커 너머의 소리가 어색하게 뚝- 끊어진다.",
    "relate_value": null,
    "occur_condition": null,
    "occur_value": [],
    "occur_prob": null,
    "result_value": [],
    "result_count": null,
    "result_prob": [],
    "is_renew_page": null
  },
  {
    "page_id": 101,
    "type": "button",
    "output_txt": "무슨 일이지…? 왠지 불안하네…",
    "relate_value": null,
    "occur_condition": null,
    "occur_value": [],
    "occur_prob": null,
    "result_value": [1011],
    "result_count": null,
    "result_prob": [],
    "is_renew_page": null
  },
  {
    "page_id": 101,
    "type": "button",
    "output_txt": "어차피 휴일이라 나갈 생각 없는데 뭐.",
    "relate_value": null,
    "occur_condition": null,
    "occur_value": [],
    "occur_prob": null,
    "result_value": [1012],
    "result_count": null,
    "result_prob": [],
    "is_renew_page": null
  },
  {
    "page_id": 1011,
    "type": "text",
    "output_txt": "불안함을 느낀 당신은 어머니에게 전화를 걸었다. 그러나 연결음만 계속될 뿐, 어머니의 목소리는 들려오지 않았다.",
    "relate_value": null,
    "occur_condition": null,
    "occur_value": [],
    "occur_prob": null,
    "result_value": [],
    "result_count": null,
    "result_prob": [],
    "is_renew_page": null
  },
  {
    "page_id": 1011,
    "type": "button",
    "output_txt": "다음",
    "relate_value": null,
    "occur_condition": null,
    "occur_value": [],
    "occur_prob": null,
    "result_value": [102],
    "result_count": null,
    "result_prob": [],
    "is_renew_page": null
  },
  {
    "page_id": 1012,
    "type": "text",
    "output_txt": "어머니의 전화를 대수롭지 않게 생각한 당신은 침대에서 나와 기지개를 켰다. 찌뿌둥하던 몸이 조금 개운해졌다.",
    "relate_value": null,
    "occur_condition": null,
    "occur_value": [],
    "occur_prob": null,
    "result_value": [],
    "result_count": null,
    "result_prob": [],
    "is_renew_page": null
  },
  {
    "page_id": 1012,
    "type": "button",
    "output_txt": "다음",
    "relate_value": null,
    "occur_condition": null,
    "occur_value": [],
    "occur_prob": null,
    "result_value": [102],
    "result_count": null,
    "result_prob": [],
    "is_renew_page": null
  },
  {
    "page_id": 102,
    "type": "text",
    "output_txt": "당신은 일단 거실로 나왔다. 베란다 창 너머로 바깥 풍경이 보인다. 그런데 어쩐지 바깥 풍경이 평소와 다른 것만 같다.",
    "relate_value": null,
    "occur_condition": null,
    "occur_value": [],
    "occur_prob": null,
    "result_value": [],
    "result_count": null,
    "result_prob": [],
    "is_renew_page": true
  },
  {
    "page_id": 102,
    "type": "img",
    "output_txt": null,
    "relate_value": "img_purple_sky",
    "occur_condition": null,
    "occur_value": [],
    "occur_prob": null,
    "result_value": [],
    "result_count": null,
    "result_prob": [],
    "is_renew_page": null
  },
  {
    "page_id": 102,
    "type": "text",
    "output_txt": "보랏빛 하늘. 가만히 창밖을 보던 당신은 하늘이 이상한 것을 깨달았다. 오전 11시, 한창 푸르게 빛나야 할 하늘이 왜 저런 빛을 띠는 것일까. 왠지 모를 불길함이 당신을 덮쳐 왔다.",
    "relate_value": null,
    "occur_condition": null,
    "occur_value": [],
    "occur_prob": null,
    "result_value": [],
    "result_count": null,
    "result_prob": [],
    "is_renew_page": null
  },
  {
    "page_id": 102,
    "type": "button",
    "output_txt": "TV를 켜 보자.",
    "relate_value": null,
    "occur_condition": null,
    "occur_value": [],
    "occur_prob": null,
    "result_value": [1021],
    "result_count": null,
    "result_prob": [],
    "is_renew_page": null
  },
  {
    "page_id": 102,
    "type": "button",
    "output_txt": "SNS에 뭔가 올라왔을지도 몰라.",
    "relate_value": null,
    "occur_condition": null,
    "occur_value": [],
    "occur_prob": null,
    "result_value": [1022],
    "result_count": null,
    "result_prob": [],
    "is_renew_page": null
  },
  {
    "page_id": 102,
    "type": "button",
    "output_txt": "베란다로 나가 봐야겠어.",
    "relate_value": null,
    "occur_condition": null,
    "occur_value": [],
    "occur_prob": null,
    "result_value": [1023],
    "result_count": null,
    "result_prob": [],
    "is_renew_page": null
  },
  {
    "page_id": 1021,
    "type": "text",
    "output_txt": "[<속보> 전세계 곳곳에서 괴현상 발생]\nTV를 켜자 예능 화면 위로 뉴스 속보 자막이 떠 있는 게 보인다. 당신은 채널을 돌려 뉴스를 틀었다.\n\"…뿐만 아니라 괴생명체가 출현하여 시민들을 공격하고 있으며, 정부가 빠르게 군대를 동원하였으나…\"\n괴생명체, 정부, 군대…. 믿을 수 없는 이야기가 TV에서 흘러나오고 있었다.",
    "relate_value": null,
    "occur_condition": null,
    "occur_value": [],
    "occur_prob": null,
    "result_value": [],
    "result_count": null,
    "result_prob": [],
    "is_renew_page": null
  },
  {
    "page_id": 1021,
    "type": "button",
    "output_txt": "다음",
    "relate_value": null,
    "occur_condition": null,
    "occur_value": [],
    "occur_prob": null,
    "result_value": [103],
    "result_count": null,
    "result_prob": [],
    "is_renew_page": null
  },
  {
    "page_id": 1022,
    "type": "text",
    "output_txt": "SNS에 들어가자 최근 게시물에 낯선 영상이 보였다. 엉망진창으로 찍힌 짧은 영상에는 게임에서나 나올 것 같은 괴생명체가 담겨 있었다.\n당신은 빠르게 SNS를 훑었다. 괴생명체가 찍힌 영상이나 사진은 한두 개가 아니었다.\n[미친; 살려줘 ㅅㅂ..\n댓글: 뭐야 실제임?????\n댓글: 야 이거 찍은애 죽은 거 아니냐..\n댓글: CG 아니고 진짜라고??\n댓글: 이야 요즘 영화 홍보 신박하게 하넼ㅋㅋㅋㅋ\n댓글: 이거 영화 아니고 실제임;;]\n영화 촬영이나 홍보쯤으로 생각하는 사람들도 있는 듯했지만, 당신이 보기에 이 상황은 실제였다.",
    "relate_value": null,
    "occur_condition": null,
    "occur_value": [],
    "occur_prob": null,
    "result_value": [],
    "result_count": null,
    "result_prob": [],
    "is_renew_page": null
  },
  {
    "page_id": 1022,
    "type": "button",
    "output_txt": "다음",
    "relate_value": null,
    "occur_condition": null,
    "occur_value": [],
    "occur_prob": null,
    "result_value": [103],
    "result_count": null,
    "result_prob": [],
    "is_renew_page": null
  },
  {
    "page_id": 1023,
    "type": "text",
    "output_txt": "베란다 밖으로 나가려던 당신은 걸음을 멈췄다. 굳이 나가지 않아도 바깥 풍경이 잘 보였기 때문이다.\n저기 멀리 길가에 피를 흘리고 쓰러진 사람이 있었다. 그리고 그 옆엔… 괴물. 게임에서 봤던 몬스터같이 생긴 무언가가 사람들을 공격하고 있다.\n도무지 믿어지지 않는 상황에 당신은 몇 번이나 눈을 깜박이고 뺨을 때려도 봤지만 풍경은 바뀌지 않았다. 이 말도 안 되는 상황이 실제인 것이다.",
    "relate_value": null,
    "occur_condition": null,
    "occur_value": [],
    "occur_prob": null,
    "result_value": [],
    "result_count": null,
    "result_prob": [],
    "is_renew_page": null
  },
  {
    "page_id": 1023,
    "type": "button",
    "output_txt": "다음",
    "relate_value": null,
    "occur_condition": null,
    "occur_value": [],
    "occur_prob": null,
    "result_value": [103],
    "result_count": null,
    "result_prob": [],
    "is_renew_page": null
  },
  {
    "page_id": 103,
    "type": "text",
    "output_txt": "당신은 이제야 어머니가 전화를 건 이유를 알았다. 엄마가 집에서 나가지 말라고 했던 건 바로 저 괴물들을 봤기 때문이 분명했다…!",
    "relate_value": null,
    "occur_condition": null,
    "occur_value": [],
    "occur_prob": null,
    "result_value": [],
    "result_count": null,
    "result_prob": [],
    "is_renew_page": true
  },
  {
    "page_id": 103,
    "type": "button",
    "output_txt": "잠깐, 그럼 엄마는…?",
    "relate_value": null,
    "occur_condition": null,
    "occur_value": [],
    "occur_prob": null,
    "result_value": [104],
    "result_count": null,
    "result_prob": [],
    "is_renew_page": null
  },
  {
    "page_id": 104,
    "type": "text",
    "output_txt": "당신은 주먹을 꽉 쥐었다. 엄마는 절대 집 밖으로 나오지 말라고 했지만 그럴 수 없었다. 왜냐하면 당신은 가족을 버려둔 채 혼자 몸을 숨길 바에야, 가족과 함께 위험 속으로 뛰어들 사람이었으므로.",
    "relate_value": null,
    "occur_condition": null,
    "occur_value": [],
    "occur_prob": null,
    "result_value": [],
    "result_count": null,
    "result_prob": [],
    "is_renew_page": true
  },
  {
    "page_id": 104,
    "type": "button",
    "output_txt": "나만 안전하게 있을 순 없어.",
    "relate_value": null,
    "occur_condition": null,
    "occur_value": [],
    "occur_prob": null,
    "result_value": [105],
    "result_count": null,
    "result_prob": [],
    "is_renew_page": null
  },
  {
    "page_id": 105,
    "type": "recursive_group",
    "output_txt": "결심을 마친 당신은 휴대폰을 주머니에 넣은 뒤 집을 둘러보았다.\n밖으로 나가는 건 좋지만 아무런 대비도 없이 나갈 수는 없다. 이럴 때일수록 신중하게, 필요한 것들을 챙겨야 했다.",
    "relate_value": null,
    "occur_condition": null,
    "occur_value": [],
    "occur_prob": null,
    "result_value": [1051, 1052, 1053, 1054, 1055, 1056, 1057, 1058],
    "result_count": 3,
    "result_prob": [1,1,1,1,1,1,1,1],
    "is_renew_page": true
  },
  {
    "page_id": 1051,
    "type": "button",
    "output_txt": "골프채",
    "relate_value": null,
    "occur_condition": null,
    "occur_value": [],
    "occur_prob": null,
    "result_value": [10511],
    "result_count": null,
    "result_prob": [],
    "is_renew_page": null
  },
  {
    "page_id": 1052,
    "type": "button",
    "output_txt": "부엌칼",
    "relate_value": null,
    "occur_condition": null,
    "occur_value": [],
    "occur_prob": null,
    "result_value": [10521],
    "result_count": null,
    "result_prob": [],
    "is_renew_page": null
  },
  {
    "page_id": 1053,
    "type": "button",
    "output_txt": "우산",
    "relate_value": null,
    "occur_condition": null,
    "occur_value": [],
    "occur_prob": null,
    "result_value": [10531],
    "result_count": null,
    "result_prob": [],
    "is_renew_page": null
  },
  {
    "page_id": 1054,
    "type": "button",
    "output_txt": "망원경",
    "relate_value": null,
    "occur_condition": null,
    "occur_value": [],
    "occur_prob": null,
    "result_value": [10541],
    "result_count": null,
    "result_prob": [],
    "is_renew_page": null
  },
  {
    "page_id": 1055,
    "type": "button",
    "output_txt": "구급약품",
    "relate_value": null,
    "occur_condition": null,
    "occur_value": [],
    "occur_prob": null,
    "result_value": [10551],
    "result_count": null,
    "result_prob": [],
    "is_renew_page": null
  },
  {
    "page_id": 1056,
    "type": "button",
    "output_txt": "장갑",
    "relate_value": null,
    "occur_condition": null,
    "occur_value": [],
    "occur_prob": null,
    "result_value": [10561],
    "result_count": null,
    "result_prob": [],
    "is_renew_page": null
  },
  {
    "page_id": 1057,
    "type": "button",
    "output_txt": "망치",
    "relate_value": null,
    "occur_condition": null,
    "occur_value": [],
    "occur_prob": null,
    "result_value": [10571],
    "result_count": null,
    "result_prob": [],
    "is_renew_page": null
  },
  {
    "page_id": 1058,
    "type": "button",
    "output_txt": "기타",
    "relate_value": null,
    "occur_condition": null,
    "occur_value": [],
    "occur_prob": null,
    "result_value": [10581],
    "result_count": null,
    "result_prob": [],
    "is_renew_page": null
  },
  {
    "page_id": 10511,
    "type": "text",
    "output_txt": "당신은 아버지의 골프채를 챙겼다.",
    "relate_value": null,
    "occur_condition": null,
    "occur_value": [],
    "occur_prob": null,
    "result_value": [],
    "result_count": null,
    "result_prob": [],
    "is_renew_page": null
  },
  {
    "page_id": 10511,
    "type": "button",
    "output_txt": "다음",
    "relate_value": null,
    "occur_condition": null,
    "occur_value": [],
    "occur_prob": null,
    "result_value": [106],
    "result_count": null,
    "result_prob": [],
    "is_renew_page": null
  },
  {
    "page_id": 10521,
    "type": "text",
    "output_txt": "당신은 주방에서 부엌칼을 챙겼다.",
    "relate_value": null,
    "occur_condition": null,
    "occur_value": [],
    "occur_prob": null,
    "result_value": [],
    "result_count": null,
    "result_prob": [],
    "is_renew_page": null
  },
  {
    "page_id": 10521,
    "type": "button",
    "output_txt": "다음",
    "relate_value": null,
    "occur_condition": null,
    "occur_value": [],
    "occur_prob": null,
    "result_value": [106],
    "result_count": null,
    "result_prob": [],
    "is_renew_page": null
  },
  {
    "page_id": 10531,
    "type": "text",
    "output_txt": "당신은 길고 튼튼한 우산을 챙겼다.",
    "relate_value": null,
    "occur_condition": null,
    "occur_value": [],
    "occur_prob": null,
    "result_value": [],
    "result_count": null,
    "result_prob": [],
    "is_renew_page": null
  },
  {
    "page_id": 10531,
    "type": "button",
    "output_txt": "다음",
    "relate_value": null,
    "occur_condition": null,
    "occur_value": [],
    "occur_prob": null,
    "result_value": [106],
    "result_count": null,
    "result_prob": [],
    "is_renew_page": null
  },
  {
    "page_id": 10541,
    "type": "text",
    "output_txt": "당신은 방구석에 처박아 두었던 망원경을 챙겼다.",
    "relate_value": null,
    "occur_condition": null,
    "occur_value": [],
    "occur_prob": null,
    "result_value": [],
    "result_count": null,
    "result_prob": [],
    "is_renew_page": null
  },
  {
    "page_id": 10541,
    "type": "button",
    "output_txt": "다음",
    "relate_value": null,
    "occur_condition": null,
    "occur_value": [],
    "occur_prob": null,
    "result_value": [106],
    "result_count": null,
    "result_prob": [],
    "is_renew_page": null
  },
  {
    "page_id": 10551,
    "type": "text",
    "output_txt": "당신은 집에 남아 있던 구급약품을 챙겼다.",
    "relate_value": null,
    "occur_condition": null,
    "occur_value": [],
    "occur_prob": null,
    "result_value": [],
    "result_count": null,
    "result_prob": [],
    "is_renew_page": null
  },
  {
    "page_id": 10551,
    "type": "button",
    "output_txt": "다음",
    "relate_value": null,
    "occur_condition": null,
    "occur_value": [],
    "occur_prob": null,
    "result_value": [106],
    "result_count": null,
    "result_prob": [],
    "is_renew_page": null
  },
  {
    "page_id": 10561,
    "type": "text",
    "output_txt": "당신은 두껍고 튼튼한 장갑을 챙겼다.",
    "relate_value": null,
    "occur_condition": null,
    "occur_value": [],
    "occur_prob": null,
    "result_value": [],
    "result_count": null,
    "result_prob": [],
    "is_renew_page": null
  },
  {
    "page_id": 10561,
    "type": "button",
    "output_txt": "다음",
    "relate_value": null,
    "occur_condition": null,
    "occur_value": [],
    "occur_prob": null,
    "result_value": [106],
    "result_count": null,
    "result_prob": [],
    "is_renew_page": null
  },
  {
    "page_id": 10571,
    "type": "text",
    "output_txt": "당신은 크고 단단한 망치를 챙겼다.",
    "relate_value": null,
    "occur_condition": null,
    "occur_value": [],
    "occur_prob": null,
    "result_value": [],
    "result_count": null,
    "result_prob": [],
    "is_renew_page": null
  },
  {
    "page_id": 10571,
    "type": "button",
    "output_txt": "다음",
    "relate_value": null,
    "occur_condition": null,
    "occur_value": [],
    "occur_prob": null,
    "result_value": [106],
    "result_count": null,
    "result_prob": [],
    "is_renew_page": null
  },
  {
    "page_id": 10581,
    "type": "text",
    "output_txt": "당신은 여차하면 무기로도 쓸 수 있는 기타를 챙겼다.",
    "relate_value": null,
    "occur_condition": null,
    "occur_value": [],
    "occur_prob": null,
    "result_value": [],
    "result_count": null,
    "result_prob": [],
    "is_renew_page": null
  },
  {
    "page_id": 10581,
    "type": "button",
    "output_txt": "다음",
    "relate_value": null,
    "occur_condition": null,
    "occur_value": [],
    "occur_prob": null,
    "result_value": [106],
    "result_count": null,
    "result_prob": [],
    "is_renew_page": null
  },
  {
    "page_id": 106,
    "type": "recursive_group",
    "output_txt": "아직 준비가 충분하지 않다고 생각한 당신은 좀 더 집을 둘러봤다.\n더 챙길 것이 없을까? 고민에 빠진 당신의 시선이 빠르게 집 안을 훑었다.",
    "relate_value": null,
    "occur_condition": null,
    "occur_value": [],
    "occur_prob": null,
    "result_value": [1061, 1062, 1063, 1064, 1065, 1066, 1067, 1068],
    "result_count": 3,
    "result_prob": [1,1,1,1,1,1,1,1],
    "is_renew_page": true
  },
  {
    "page_id": 1061,
    "type": "button",
    "output_txt": "골프채",
    "relate_value": null,
    "occur_condition": null,
    "occur_value": [],
    "occur_prob": null,
    "result_value": [10611],
    "result_count": null,
    "result_prob": [],
    "is_renew_page": null
  },
  {
    "page_id": 1062,
    "type": "button",
    "output_txt": "부엌칼",
    "relate_value": null,
    "occur_condition": null,
    "occur_value": [],
    "occur_prob": null,
    "result_value": [10621],
    "result_count": null,
    "result_prob": [],
    "is_renew_page": null
  },
  {
    "page_id": 1063,
    "type": "button",
    "output_txt": "우산",
    "relate_value": null,
    "occur_condition": null,
    "occur_value": [],
    "occur_prob": null,
    "result_value": [10631],
    "result_count": null,
    "result_prob": [],
    "is_renew_page": null
  },
  {
    "page_id": 1064,
    "type": "button",
    "output_txt": "망원경",
    "relate_value": null,
    "occur_condition": null,
    "occur_value": [],
    "occur_prob": null,
    "result_value": [10641],
    "result_count": null,
    "result_prob": [],
    "is_renew_page": null
  },
  {
    "page_id": 1065,
    "type": "button",
    "output_txt": "구급약품",
    "relate_value": null,
    "occur_condition": null,
    "occur_value": [],
    "occur_prob": null,
    "result_value": [10651],
    "result_count": null,
    "result_prob": [],
    "is_renew_page": null
  },
  {
    "page_id": 1066,
    "type": "button",
    "output_txt": "장갑",
    "relate_value": null,
    "occur_condition": null,
    "occur_value": [],
    "occur_prob": null,
    "result_value": [10661],
    "result_count": null,
    "result_prob": [],
    "is_renew_page": null
  },
  {
    "page_id": 1067,
    "type": "button",
    "output_txt": "망치",
    "relate_value": null,
    "occur_condition": null,
    "occur_value": [],
    "occur_prob": null,
    "result_value": [10671],
    "result_count": null,
    "result_prob": [],
    "is_renew_page": null
  },
  {
    "page_id": 1068,
    "type": "button",
    "output_txt": "기타",
    "relate_value": null,
    "occur_condition": null,
    "occur_value": [],
    "occur_prob": null,
    "result_value": [10681],
    "result_count": null,
    "result_prob": [],
    "is_renew_page": null
  },
  {
    "page_id": 10611,
    "type": "text",
    "output_txt": "당신은 아버지의 골프채를 챙겼다.",
    "relate_value": null,
    "occur_condition": null,
    "occur_value": [],
    "occur_prob": null,
    "result_value": [],
    "result_count": null,
    "result_prob": [],
    "is_renew_page": null
  },
  {
    "page_id": 10611,
    "type": "button",
    "output_txt": "다음",
    "relate_value": null,
    "occur_condition": null,
    "occur_value": [],
    "occur_prob": null,
    "result_value": [107],
    "result_count": null,
    "result_prob": [],
    "is_renew_page": null
  },
  {
    "page_id": 10621,
    "type": "text",
    "output_txt": "당신은 주방에서 부엌칼을 챙겼다.",
    "relate_value": null,
    "occur_condition": null,
    "occur_value": [],
    "occur_prob": null,
    "result_value": [],
    "result_count": null,
    "result_prob": [],
    "is_renew_page": null
  },
  {
    "page_id": 10621,
    "type": "button",
    "output_txt": "다음",
    "relate_value": null,
    "occur_condition": null,
    "occur_value": [],
    "occur_prob": null,
    "result_value": [107],
    "result_count": null,
    "result_prob": [],
    "is_renew_page": null
  },
  {
    "page_id": 10631,
    "type": "text",
    "output_txt": "당신은 길고 튼튼한 우산을 챙겼다.",
    "relate_value": null,
    "occur_condition": null,
    "occur_value": [],
    "occur_prob": null,
    "result_value": [],
    "result_count": null,
    "result_prob": [],
    "is_renew_page": null
  },
  {
    "page_id": 10631,
    "type": "button",
    "output_txt": "다음",
    "relate_value": null,
    "occur_condition": null,
    "occur_value": [],
    "occur_prob": null,
    "result_value": [107],
    "result_count": null,
    "result_prob": [],
    "is_renew_page": null
  },
  {
    "page_id": 10641,
    "type": "text",
    "output_txt": "당신은 방구석에 처박아 두었던 망원경을 챙겼다.",
    "relate_value": null,
    "occur_condition": null,
    "occur_value": [],
    "occur_prob": null,
    "result_value": [],
    "result_count": null,
    "result_prob": [],
    "is_renew_page": null
  },
  {
    "page_id": 10641,
    "type": "button",
    "output_txt": "다음",
    "relate_value": null,
    "occur_condition": null,
    "occur_value": [],
    "occur_prob": null,
    "result_value": [107],
    "result_count": null,
    "result_prob": [],
    "is_renew_page": null
  },
  {
    "page_id": 10651,
    "type": "text",
    "output_txt": "당신은 집에 남아 있던 구급약품을 챙겼다.",
    "relate_value": null,
    "occur_condition": null,
    "occur_value": [],
    "occur_prob": null,
    "result_value": [],
    "result_count": null,
    "result_prob": [],
    "is_renew_page": null
  },
  {
    "page_id": 10651,
    "type": "button",
    "output_txt": "다음",
    "relate_value": null,
    "occur_condition": null,
    "occur_value": [],
    "occur_prob": null,
    "result_value": [107],
    "result_count": null,
    "result_prob": [],
    "is_renew_page": null
  },
  {
    "page_id": 10661,
    "type": "text",
    "output_txt": "당신은 두껍고 튼튼한 장갑을 챙겼다.",
    "relate_value": null,
    "occur_condition": null,
    "occur_value": [],
    "occur_prob": null,
    "result_value": [],
    "result_count": null,
    "result_prob": [],
    "is_renew_page": null
  },
  {
    "page_id": 10661,
    "type": "button",
    "output_txt": "다음",
    "relate_value": null,
    "occur_condition": null,
    "occur_value": [],
    "occur_prob": null,
    "result_value": [107],
    "result_count": null,
    "result_prob": [],
    "is_renew_page": null
  },
  {
    "page_id": 10671,
    "type": "text",
    "output_txt": "당신은 크고 단단한 망치를 챙겼다.",
    "relate_value": null,
    "occur_condition": null,
    "occur_value": [],
    "occur_prob": null,
    "result_value": [],
    "result_count": null,
    "result_prob": [],
    "is_renew_page": null
  },
  {
    "page_id": 10671,
    "type": "button",
    "output_txt": "다음",
    "relate_value": null,
    "occur_condition": null,
    "occur_value": [],
    "occur_prob": null,
    "result_value": [107],
    "result_count": null,
    "result_prob": [],
    "is_renew_page": null
  },
  {
    "page_id": 10681,
    "type": "text",
    "output_txt": "당신은 여차하면 무기로도 쓸 수 있는 기타를 챙겼다.",
    "relate_value": null,
    "occur_condition": null,
    "occur_value": [],
    "occur_prob": null,
    "result_value": [],
    "result_count": null,
    "result_prob": [],
    "is_renew_page": null
  },
  {
    "page_id": 10681,
    "type": "button",
    "output_txt": "다음",
    "relate_value": null,
    "occur_condition": null,
    "occur_value": [],
    "occur_prob": null,
    "result_value": [107],
    "result_count": null,
    "result_prob": [],
    "is_renew_page": null
  },
  {
    "page_id": 107,
    "type": "recursive_group",
    "output_txt": "당신은 마지막으로 상황을 점검했다.\n이대로 나가자니 왠지 허전한 기분이다. 뭔가 하나쯤 더 챙기면 좋을 것 같았다.",
    "relate_value": null,
    "occur_condition": null,
    "occur_value": [],
    "occur_prob": null,
    "result_value": [1071, 1072, 1073, 1074, 1075, 1076, 1077, 1078],
    "result_count": 3,
    "result_prob": [1,1,1,1,1,1,1,1],
    "is_renew_page": true
  },
  {
    "page_id": 1071,
    "type": "button",
    "output_txt": "골프채",
    "relate_value": null,
    "occur_condition": null,
    "occur_value": [],
    "occur_prob": null,
    "result_value": [10711],
    "result_count": null,
    "result_prob": [],
    "is_renew_page": null
  },
  {
    "page_id": 1072,
    "type": "button",
    "output_txt": "부엌칼",
    "relate_value": null,
    "occur_condition": null,
    "occur_value": [],
    "occur_prob": null,
    "result_value": [10721],
    "result_count": null,
    "result_prob": [],
    "is_renew_page": null
  },
  {
    "page_id": 1073,
    "type": "button",
    "output_txt": "우산",
    "relate_value": null,
    "occur_condition": null,
    "occur_value": [],
    "occur_prob": null,
    "result_value": [10731],
    "result_count": null,
    "result_prob": [],
    "is_renew_page": null
  },
  {
    "page_id": 1074,
    "type": "button",
    "output_txt": "망원경",
    "relate_value": null,
    "occur_condition": null,
    "occur_value": [],
    "occur_prob": null,
    "result_value": [10741],
    "result_count": null,
    "result_prob": [],
    "is_renew_page": null
  },
  {
    "page_id": 1075,
    "type": "button",
    "output_txt": "구급약품",
    "relate_value": null,
    "occur_condition": null,
    "occur_value": [],
    "occur_prob": null,
    "result_value": [10751],
    "result_count": null,
    "result_prob": [],
    "is_renew_page": null
  },
  {
    "page_id": 1076,
    "type": "button",
    "output_txt": "장갑",
    "relate_value": null,
    "occur_condition": null,
    "occur_value": [],
    "occur_prob": null,
    "result_value": [10761],
    "result_count": null,
    "result_prob": [],
    "is_renew_page": null
  },
  {
    "page_id": 1077,
    "type": "button",
    "output_txt": "망치",
    "relate_value": null,
    "occur_condition": null,
    "occur_value": [],
    "occur_prob": null,
    "result_value": [10771],
    "result_count": null,
    "result_prob": [],
    "is_renew_page": null
  },
  {
    "page_id": 1078,
    "type": "button",
    "output_txt": "기타",
    "relate_value": null,
    "occur_condition": null,
    "occur_value": [],
    "occur_prob": null,
    "result_value": [10781],
    "result_count": null,
    "result_prob": [],
    "is_renew_page": null
  },
  {
    "page_id": 10711,
    "type": "text",
    "output_txt": "당신은 아버지의 골프채를 챙겼다.",
    "relate_value": null,
    "occur_condition": null,
    "occur_value": [],
    "occur_prob": null,
    "result_value": [],
    "result_count": null,
    "result_prob": [],
    "is_renew_page": null
  },
  {
    "page_id": 10711,
    "type": "button",
    "output_txt": "다음",
    "relate_value": null,
    "occur_condition": null,
    "occur_value": [],
    "occur_prob": null,
    "result_value": [108],
    "result_count": null,
    "result_prob": [],
    "is_renew_page": null
  },
  {
    "page_id": 10721,
    "type": "text",
    "output_txt": "당신은 주방에서 부엌칼을 챙겼다.",
    "relate_value": null,
    "occur_condition": null,
    "occur_value": [],
    "occur_prob": null,
    "result_value": [],
    "result_count": null,
    "result_prob": [],
    "is_renew_page": null
  },
  {
    "page_id": 10721,
    "type": "button",
    "output_txt": "다음",
    "relate_value": null,
    "occur_condition": null,
    "occur_value": [],
    "occur_prob": null,
    "result_value": [108],
    "result_count": null,
    "result_prob": [],
    "is_renew_page": null
  },
  {
    "page_id": 10731,
    "type": "text",
    "output_txt": "당신은 길고 튼튼한 우산을 챙겼다.",
    "relate_value": null,
    "occur_condition": null,
    "occur_value": [],
    "occur_prob": null,
    "result_value": [],
    "result_count": null,
    "result_prob": [],
    "is_renew_page": null
  },
  {
    "page_id": 10731,
    "type": "button",
    "output_txt": "다음",
    "relate_value": null,
    "occur_condition": null,
    "occur_value": [],
    "occur_prob": null,
    "result_value": [108],
    "result_count": null,
    "result_prob": [],
    "is_renew_page": null
  },
  {
    "page_id": 10741,
    "type": "text",
    "output_txt": "당신은 방구석에 처박아 두었던 망원경을 챙겼다.",
    "relate_value": null,
    "occur_condition": null,
    "occur_value": [],
    "occur_prob": null,
    "result_value": [],
    "result_count": null,
    "result_prob": [],
    "is_renew_page": null
  },
  {
    "page_id": 10741,
    "type": "button",
    "output_txt": "다음",
    "relate_value": null,
    "occur_condition": null,
    "occur_value": [],
    "occur_prob": null,
    "result_value": [108],
    "result_count": null,
    "result_prob": [],
    "is_renew_page": null
  },
  {
    "page_id": 10751,
    "type": "text",
    "output_txt": "당신은 집에 남아 있던 구급약품을 챙겼다.",
    "relate_value": null,
    "occur_condition": null,
    "occur_value": [],
    "occur_prob": null,
    "result_value": [],
    "result_count": null,
    "result_prob": [],
    "is_renew_page": null
  },
  {
    "page_id": 10751,
    "type": "button",
    "output_txt": "다음",
    "relate_value": null,
    "occur_condition": null,
    "occur_value": [],
    "occur_prob": null,
    "result_value": [108],
    "result_count": null,
    "result_prob": [],
    "is_renew_page": null
  },
  {
    "page_id": 10761,
    "type": "text",
    "output_txt": "당신은 두껍고 튼튼한 장갑을 챙겼다.",
    "relate_value": null,
    "occur_condition": null,
    "occur_value": [],
    "occur_prob": null,
    "result_value": [],
    "result_count": null,
    "result_prob": [],
    "is_renew_page": null
  },
  {
    "page_id": 10761,
    "type": "button",
    "output_txt": "다음",
    "relate_value": null,
    "occur_condition": null,
    "occur_value": [],
    "occur_prob": null,
    "result_value": [108],
    "result_count": null,
    "result_prob": [],
    "is_renew_page": null
  },
  {
    "page_id": 10771,
    "type": "text",
    "output_txt": "당신은 크고 단단한 망치를 챙겼다.",
    "relate_value": null,
    "occur_condition": null,
    "occur_value": [],
    "occur_prob": null,
    "result_value": [],
    "result_count": null,
    "result_prob": [],
    "is_renew_page": null
  },
  {
    "page_id": 10771,
    "type": "button",
    "output_txt": "다음",
    "relate_value": null,
    "occur_condition": null,
    "occur_value": [],
    "occur_prob": null,
    "result_value": [108],
    "result_count": null,
    "result_prob": [],
    "is_renew_page": null
  },
  {
    "page_id": 10781,
    "type": "text",
    "output_txt": "당신은 여차하면 무기로도 쓸 수 있는 기타를 챙겼다.",
    "relate_value": null,
    "occur_condition": null,
    "occur_value": [],
    "occur_prob": null,
    "result_value": [],
    "result_count": null,
    "result_prob": [],
    "is_renew_page": null
  },
  {
    "page_id": 10781,
    "type": "button",
    "output_txt": "다음",
    "relate_value": null,
    "occur_condition": null,
    "occur_value": [],
    "occur_prob": null,
    "result_value": [108],
    "result_count": null,
    "result_prob": [],
    "is_renew_page": null
  },
  {
    "page_id": 108,
    "type": "text",
    "output_txt": "당신은 이만하면 충분하다고 생각했다. 더는 시간을 지체할 수 없었다. 이제 정말로 나가야 할 때였다.",
    "relate_value": null,
    "occur_condition": null,
    "occur_value": [],
    "occur_prob": null,
    "result_value": [],
    "result_count": null,
    "result_prob": [],
    "is_renew_page": true
  },
  {
    "page_id": 108,
    "type": "button",
    "output_txt": "좋아… 이제 나가자!",
    "relate_value": null,
    "occur_condition": null,
    "occur_value": [],
    "occur_prob": null,
    "result_value": [109, 110],
    "result_count": null,
    "result_prob": [1,1],
    "is_renew_page": null
  },
  {
    "page_id": 109,
    "type": "text",
    "output_txt": "집 밖으로 나온 당신은 엘리베이터를 기다렸다. 그러나 엘리베이터는 최고층에서 멈춘 채, 한참을 움직이지 않는다.\n지금 당신이 있는 곳은 13층. 계단을 이용한다면 한참을 걸어 내려가야 한다.",
    "relate_value": null,
    "occur_condition": null,
    "occur_value": [],
    "occur_prob": null,
    "result_value": [],
    "result_count": null,
    "result_prob": [],
    "is_renew_page": true
  },
  {
    "page_id": 109,
    "type": "button",
    "output_txt": "더는 못 기다리겠어.",
    "relate_value": null,
    "occur_condition": null,
    "occur_value": [],
    "occur_prob": null,
    "result_value": [1091],
    "result_count": null,
    "result_prob": [],
    "is_renew_page": null
  },
  {
    "page_id": 109,
    "type": "button",
    "output_txt": "조금만 더 기다려 보자….",
    "relate_value": null,
    "occur_condition": null,
    "occur_value": [],
    "occur_prob": null,
    "result_value": [1092],
    "result_count": null,
    "result_prob": [],
    "is_renew_page": null
  },
  {
    "page_id": 1091,
    "type": "text",
    "output_txt": "당신은 계단을 통해 1층으로 내려갔다. 출입문 앞에 서서 엘리베이터를 보니 여전히 최고층이다.\n다리가 좀 아프긴 하지만 계단을 이용하길 잘했다고, 그렇게 생각하며 당신은 출입문을 지났다.",
    "relate_value": null,
    "occur_condition": null,
    "occur_value": [],
    "occur_prob": null,
    "result_value": [],
    "result_count": null,
    "result_prob": [],
    "is_renew_page": null
  },
  {
    "page_id": 1091,
    "type": "button",
    "output_txt": "다음",
    "relate_value": null,
    "occur_condition": null,
    "occur_value": [],
    "occur_prob": null,
    "result_value": [],
    "result_count": null,
    "result_prob": [],
    "is_renew_page": null
  },
  {
    "page_id": 1092,
    "type": "text",
    "output_txt": "당신은 10분을 더 기다렸다. 최고층에서 꿈쩍도 하지 않던 엘리베이터가 드디어 내려오기 시작했다.",
    "relate_value": null,
    "occur_condition": null,
    "occur_value": [],
    "occur_prob": null,
    "result_value": [],
    "result_count": null,
    "result_prob": [],
    "is_renew_page": null
  },
  {
    "page_id": 1092,
    "type": "img",
    "output_txt": null,
    "relate_value": "img_elevator",
    "occur_condition": null,
    "occur_value": [],
    "occur_prob": null,
    "result_value": [],
    "result_count": null,
    "result_prob": [],
    "is_renew_page": null
  },
  {
    "page_id": 1092,
    "type": "text",
    "output_txt": "띵동-",
    "relate_value": null,
    "occur_condition": null,
    "occur_value": [],
    "occur_prob": null,
    "result_value": [],
    "result_count": null,
    "result_prob": [],
    "is_renew_page": null
  },
  {
    "page_id": 1092,
    "type": "text",
    "output_txt": "기다리던 엘리베이터가 서고 문이 열렸다. 그런데 엘리베이터 안에 있는 사람이… 피 묻은 칼을 들고 서 있다.\n칼을 든 사람과 눈이 마주친 당신은 직감적으로 피해야 한다는 것을 느꼈다. 한 걸음, 두 걸음, 당신의 걸음이 점점 엘리베이터에서 멀어졌다. 곧, 당신은 빠르게 계단을 향해 달렸다.",
    "relate_value": null,
    "occur_condition": null,
    "occur_value": [],
    "occur_prob": null,
    "result_value": [],
    "result_count": null,
    "result_prob": [],
    "is_renew_page": null
  },
  {
    "page_id": 1092,
    "type": "button",
    "output_txt": "다음",
    "relate_value": null,
    "occur_condition": null,
    "occur_value": [],
    "occur_prob": null,
    "result_value": [],
    "result_count": null,
    "result_prob": [],
    "is_renew_page": null
  },
  {
    "page_id": 110,
    "type": "text",
    "output_txt": "다행히 엘리베이터 앞 현관은 아직 고요했다.\n최고층에 멈춰 서 있는 엘리베이터를 본 당신은 망설임 없이 계단으로 이동했다. 재난 상황에서는 엘리베이터보다 계단을 이용하는 게 더 안전하니까.",
    "relate_value": null,
    "occur_condition": null,
    "occur_value": [],
    "occur_prob": null,
    "result_value": [],
    "result_count": null,
    "result_prob": [],
    "is_renew_page": true
  },
  {
    "page_id": 110,
    "type": "text",
    "output_txt": "다음",
    "relate_value": null,
    "occur_condition": null,
    "occur_value": [],
    "occur_prob": null,
    "result_value": [],
    "result_count": null,
    "result_prob": [],
    "is_renew_page": null
  }
]